{"continue":{"iistart":"2009-04-01T07:48:57Z","continue":"||"},"query":{"pages":{"5920599":{"pageid":5920599,"ns":6,"title":"File:Lillium Stamens.jpg","imagerepository":"local","imageinfo":[{"size":1206376,"width":1296,"height":1944,"thumburl":"https://upload.wikimedia.org/wikipedia/commons/a/a4/Lillium_Stamens.jpg","thumbwidth":1296,"thumbheight":1944,"url":"https://upload.wikimedia.org/wikipedia/commons/a/a4/Lillium_Stamens.jpg","descriptionurl":"https://commons.wikimedia.org/wiki/File:Lillium_Stamens.jpg","descriptionshorturl":"https://commons.wikimedia.org/w/index.php?curid=5920599","extmetadata":{"DateTime":{"value":"2009-04-06 09:00:34","source":"mediawiki-metadata","hidden":""},"ObjectName":{"value":"Lillium Stamens","source":"mediawiki-metadata"},"CommonsMetadataExtension":{"value":1.2,"source":"extension","hidden":""},"Categories":{"value":"Taken with Canon EOS 400D|Lilium Oriental Hybrids|Floral diagrams|Stigma (botany)|Self-published work|Featured pictures on Wikipedia, English|Stamens|Featured diagrams|Photos by JJ Harrison|Files with coordinates missing SDC location of creation|Files with Assessments template missing SDC Commons no value quality assessment","source":"commons-categories","hidden":""},"Assessments":{"value":"","source":"commons-categories","hidden":""},"GPSLatitude":{"value":"-42.778340","source":"commons-desc-page"},"GPSLongitude":{"value":"147.262000","source":"commons-desc-page"},"GPSMapDatum":{"value":"WGS-84","source":"commons-desc-page","hidden":""},"ImageDescription":{"value":"Christmas Lillium. 1. Stigma, 2. Style, 3. Anthers, 4. Filament, 5. Sepal","source":"commons-desc-page"},"DateTimeOriginal":{"value":"6/01/2009","source":"commons-desc-page"},"Credit":{"value":"<span class=\"int-own-work\" lang=\"en\">Own work</span>","source":"commons-desc-page"},"Artist":{"value":"<a href=\"//commons.wikimedia.org/wiki/User:JJ_Harrison\" title=\"User:JJ Harrison\">JJ Harrison</a> (<a rel=\"nofollow\" class=\"external free\" href=\"https://www.jjharrison.com.au/\">https://www.jjharrison.com.au/</a>)","source":"commons-desc-page"},"LicenseShortName":{"value":"CC BY-SA 3.0","source":"commons-desc-page","hidden":""},"UsageTerms":{"value":"Creative Commons Attribution-Share Alike 3.0","source":"commons-desc-page"},"AttributionRequired":{"value":"true","source":"commons-desc-page","hidden":""},"LicenseUrl":{"value":"https://creativecommons.org/licenses/by-sa/3.0","source":"commons-desc-page"},"Copyrighted":{"value":"True","source":"commons-desc-page","hidden":""},"Restrictions":{"value":"","source":"commons-desc-page","hidden":""},"License":{"value":"cc-by-sa-3.0","source":"commons-templates","hidden":""}},"mime":"image/jpeg"}]}}}}